django_choices_flow
