Metadata-Version: 1.0
Name: django-choices-flow
Version: 0.8.5
Summary: Simple library with flow in choices values for Django
Home-page: https://github.com/valdergallo/django-choices-flow
Author: valdergallo
Author-email: valdergallo@gmail.com
License: FREEBSD
Keywords: Django choices flow overflow
Platform: UNKNOWN
Classifier: Framework :: Django
Classifier: Operating System :: OS Independent
Classifier: Topic :: Utilities
Classifier: Programming Language :: Python
Classifier: Programming Language :: Python :: 2.6
Classifier: Programming Language :: Python :: 2.7
Classifier: Programming Language :: Python :: 3.3
